module_A.py
module_A2.py
666-1.0.dist-info/METADATA
666-1.0.dist-info/WHEEL
666-1.0.dist-info/top_level.txt
666-1.0.dist-info/RECORD
