Metadata-Version: 2.1
Name: 666
Version: 1.0
Summary: 这个模块有点东西哦
Home-page: UNKNOWN
Author: 赵佳乐
Author-email: 488635489@qq.com
License: UNKNOWN
Platform: UNKNOWN
